{
  "posts": [
    {
      "id": "cd01",
      "titulo": "Desenvolvimento de Software",
      "nome": "Ana Silva",
      "email": "ana@empresa1.com",
      "atividade": "Criação de um novo sistema",
      "categoria": "Governança Corporativa",
      "pontuacao": 30
    },
    {
      "id": "cd02",
      "titulo": "Campanha de Publicidade",
      "nome": "Bruno Souza",
      "email": "bruno@empresa1.com",
      "atividade": "Lançamento de campanha digital",
      "categoria": "Governança Social",
      "pontuacao": 40
    },
    {
      "id": "cd03",
      "titulo": "Treinamento de Equipe",
      "nome": "Carlos Pereira",
      "email": "carlos@empresa1.com",
      "atividade": "Treinamento de novos funcionários",
      "categoria": "Governança Social",
      "pontuacao": 40
    },
    {
      "id": "cd04",
      "titulo": "Análise de Mercado",
      "nome": "Daniela Lima",
      "email": "daniela@empresa1.com",
      "atividade": "Estudo de viabilidade",
      "categoria": "Governança Corporativa",
      "pontuacao": 30
    },
    {
      "id": "cd05",
      "titulo": "Negociação com Clientes",
      "nome": "Eduardo Costa",
      "email": "eduardo@empresa1.com",
      "atividade": "Negociações comerciais",
      "categoria": "Governança Corporativa",
      "pontuacao": 30
    },
    {
      "id": "cd06",
      "titulo": "Manutenção de Sistemas",
      "nome": "Fernanda Santos",
      "email": "fernanda@empresa2.com",
      "atividade": "Manutenção de servidores",
      "categoria": "Governança Ambiental",
      "pontuacao": 50
    },
    {
      "id": "cd07",
      "titulo": "Gestão de Estoque",
      "nome": "Gabriel Oliveira",
      "email": "gabriel@empresa2.com",
      "atividade": "Controle de inventário",
      "categoria": "Governança Corporativa",
      "pontuacao": 30
    },
    {
      "id": "cd08",
      "titulo": "Suporte Técnico",
      "nome": "Helena Rodrigues",
      "email": "helena@empresa2.com",
      "atividade": "Atendimento ao cliente",
      "categoria": "Governança Social",
      "pontuacao": 40
    },
    {
      "id": "cd09",
      "titulo": "Desenvolvimento Web",
      "nome": "Igor Ferreira",
      "email": "igor@empresa3.com",
      "atividade": "Criação de sites",
      "categoria": "Governança Corporativa",
      "pontuacao": 30
    },
    {
      "id": "cd10",
      "titulo": "Fechamento de Contratos",
      "nome": "Juliana Almeida",
      "email": "juliana@empresa3.com",
      "atividade": "Contratos de vendas",
      "categoria": "Governança Corporativa",
      "pontuacao": 30
    },
    {
      "id": "cd11",
      "titulo": "Criação de Conteúdo",
      "nome": "Lucas Barbosa",
      "email": "lucas@empresa3.com",
      "atividade": "Conteúdo para redes sociais",
      "categoria": "Governança Social",
      "pontuacao": 40
    },
    {
      "id": "cd12",
      "titulo": "Recrutamento",
      "nome": "Mariana Gomes",
      "email": "mariana@empresa3.com",
      "atividade": "Seleção de candidatos",
      "categoria": "Governança Social",
      "pontuacao": 40
    },
    {
      "id": "cd13",
      "titulo": "Segurança da Informação",
      "nome": "Nicolas Alves",
      "email": "nicolas@empresa3.com",
      "atividade": "Implementação de medidas de segurança",
      "categoria": "Governança Corporativa",
      "pontuacao": 30
    },
    {
      "id": "cd14",
      "titulo": "Contabilidade",
      "nome": "Olivia Monteiro",
      "email": "olivia@empresa3.com",
      "atividade": "Gerenciamento de contas",
      "categoria": "Governança Corporativa",
      "pontuacao": 30
    },
    {
      "id": "cd15",
      "titulo": "Prospecção de Clientes",
      "nome": "Pedro Batista",
      "email": "pedro@empresa3.com",
      "atividade": "Identificação de novos clientes",
      "categoria": "Governança Corporativa",
      "pontuacao": 30
    },
    {
      "id": "cd16",
      "titulo": "Gestão de Reclamações",
      "nome": "Quésia Lima",
      "email": "quesia@empresa3.com",
      "atividade": "Atendimento a reclamações",
      "categoria": "Governança Social",
      "pontuacao": 40
    },
    {
      "id": "cd17",
      "titulo": "Distribuição",
      "nome": "Rafael Martins",
      "email": "rafael@empresa3.com",
      "atividade": "Distribuição de produtos",
      "categoria": "Governança Corporativa",
      "pontuacao": 30
    },
    {
      "id": "cd18",
      "titulo": "Desenvolvimento Mobile",
      "nome": "Sara Correia",
      "email": "sara@empresa4.com",
      "atividade": "Criação de aplicativos",
      "categoria": "Governança Ambiental",
      "pontuacao": 50
    },
    {
      "id": "cd19",
      "titulo": "SEO",
      "nome": "Tiago Ribeiro",
      "email": "tiago@empresa4.com",
      "atividade": "Otimização de sites",
      "categoria": "Governança Ambiental",
      "pontuacao": 50
    },
    {
      "id": "cd20",
      "titulo": "Análise de Dados",
      "nome": "Ursula Andrade",
      "email": "ursula@empresa5.com",
      "atividade": "Análise de grandes volumes de dados",
      "categoria": "Governança Ambiental",
      "pontuacao": 50
    },
    {
      "id": "cd21",
      "titulo": "Planejamento de Carreira",
      "nome": "Victor Nunes",
      "email": "victor@empresa6.com",
      "atividade": "Planejamento e desenvolvimento de carreira",
      "categoria": "Governança Social",
      "pontuacao": 40
    },
    {
      "id": "cd22",
      "titulo": "Planejamento Financeiro",
      "nome": "Wesley Fernandes",
      "email": "wesley@empresa7.com",
      "atividade": "Elaboração de planos financeiros",
      "categoria": "Governança Corporativa",
      "pontuacao": 30
    },
    {
      "id": "cd23",
      "titulo": "Treinamento de Vendas",
      "nome": "Ximena Lopes",
      "email": "ximena@empresa8.com",
      "atividade": "Treinamento da equipe de vendas",
      "categoria": "Governança Social",
      "pontuacao": 40
    },
    {
      "id": "cd24",
      "titulo": "Gestão de Projetos",
      "nome": "Yara Figueiredo",
      "email": "yara@empresa9.com",
      "atividade": "Gestão de projetos de TI",
      "categoria": "Governança Corporativa",
      "pontuacao": 30
    },
    {
      "id": "cd25",
      "titulo": "Chatbot",
      "nome": "Zeca Cunha",
      "email": "zeca@empresa10.com",
      "atividade": "Desenvolvimento de chatbot",
      "categoria": "Governança Social",
      "pontuacao": 40
    },
    {
      "id": "cd26",
      "titulo": "Gestão de Transportes",
      "nome": "leonardo",
      "email": "leonardoalves@empresa1.com",
      "atividade": "Gestão da frota de transportes",
      "categoria": "Governança Ambiental",
      "pontuacao": 50
    },
    {
      "id": "cd27",
      "titulo": "Email Marketing",
      "nome": "Beto Azevedo",
      "email": "beto@empresa12.com",
      "atividade": "Campanha de email marketing",
      "categoria": "Governança Social",
      "pontuacao": 40
    },
    {
      "id": "cd28",
      "titulo": "Infraestrutura de TI",
      "nome": "Cecília Cardoso",
      "email": "cecilia@empresa13.com",
      "atividade": "Gestão da infraestrutura de TI",
      "categoria": "Governança Corporativa",
      "pontuacao": 30
    },
    {
      "id": "cd29",
      "titulo": "Investimentos",
      "nome": "leonardo",
      "email": "leonardoalves@empresa1.com",
      "atividade": "Gestão de portfólio de investimentos",
      "categoria": "Governança Corporativa",
      "pontuacao": 30
    },
    {
      "id": "cd30",
      "titulo": "Avaliação de Desempenho",
      "nome": "Elisa Ramos",
      "email": "elisa@empresa15.com",
      "atividade": "Avaliação do desempenho dos funcionários",
      "categoria": "Governança Social",
      "pontuacao": 40
    },
    {
      "id": "49c3",
      "titulo": "leonardo",
      "nome": "leonardo",
      "email": "leonardoalves@empresa1.com",
      "atividade": "leonardo",
      "categoria": "Governança Corporativa",
      "pontuacao": 30
    },
    {
      "id": "a943",
      "titulo": "Plantar arvore",
      "nome": "Priscila",
      "email": "priscila@adm.com",
      "atividade": "plantei uma arvore no pico do jaragua",
      "categoria": "ambiental",
      "pontuacao": 50
    }
  ]
}